PythonYuanXuexiShiyongZhinan2021727Fix1/README.md
PythonYuanXuexiShiyongZhinan2021727Fix1/__init__.py
PythonYuanXuexiShiyongZhinan2021727Fix1/__main__.py
PythonYuanXuexiShiyongZhinan2021727Fix1/file.epub
PythonYuanXuexiShiyongZhinan2021727Fix1/index.html
PythonYuanXuexiShiyongZhinan2021727Fix1/css/__init__.py
PythonYuanXuexiShiyongZhinan2021727Fix1/css/annotations.css
PythonYuanXuexiShiyongZhinan2021727Fix1/css/main.css
PythonYuanXuexiShiyongZhinan2021727Fix1/css/normalize.css
PythonYuanXuexiShiyongZhinan2021727Fix1/css/popup.css
PythonYuanXuexiShiyongZhinan2021727Fix1/font/__init__.py
PythonYuanXuexiShiyongZhinan2021727Fix1/font/fontello.eot
PythonYuanXuexiShiyongZhinan2021727Fix1/font/fontello.svg
PythonYuanXuexiShiyongZhinan2021727Fix1/font/fontello.ttf
PythonYuanXuexiShiyongZhinan2021727Fix1/font/fontello.woff
PythonYuanXuexiShiyongZhinan2021727Fix1/img/__init__.py
PythonYuanXuexiShiyongZhinan2021727Fix1/img/annotator-glyph-sprite.png
PythonYuanXuexiShiyongZhinan2021727Fix1/img/annotator-icon-sprite.png
PythonYuanXuexiShiyongZhinan2021727Fix1/img/apple-touch-icon.png
PythonYuanXuexiShiyongZhinan2021727Fix1/img/cancelfullscreen.png
PythonYuanXuexiShiyongZhinan2021727Fix1/img/close.png
PythonYuanXuexiShiyongZhinan2021727Fix1/img/fullscreen.png
PythonYuanXuexiShiyongZhinan2021727Fix1/img/loader.gif
PythonYuanXuexiShiyongZhinan2021727Fix1/img/menu-icon.png
PythonYuanXuexiShiyongZhinan2021727Fix1/img/save.png
PythonYuanXuexiShiyongZhinan2021727Fix1/img/saved.png
PythonYuanXuexiShiyongZhinan2021727Fix1/img/settings-s.png
PythonYuanXuexiShiyongZhinan2021727Fix1/img/settings.png
PythonYuanXuexiShiyongZhinan2021727Fix1/img/star.png
PythonYuanXuexiShiyongZhinan2021727Fix1/js/__init__.py
PythonYuanXuexiShiyongZhinan2021727Fix1/js/epub.js
PythonYuanXuexiShiyongZhinan2021727Fix1/js/epub.min.js
PythonYuanXuexiShiyongZhinan2021727Fix1/js/epub.min.map
PythonYuanXuexiShiyongZhinan2021727Fix1/js/hooks.min.js
PythonYuanXuexiShiyongZhinan2021727Fix1/js/hooks.min.map
python_yuan_xuexi_shiyong_zhinan_2021_7_27_fix1-2024.3.6.0.dist-info/METADATA
python_yuan_xuexi_shiyong_zhinan_2021_7_27_fix1-2024.3.6.0.dist-info/WHEEL
python_yuan_xuexi_shiyong_zhinan_2021_7_27_fix1-2024.3.6.0.dist-info/entry_points.txt
python_yuan_xuexi_shiyong_zhinan_2021_7_27_fix1-2024.3.6.0.dist-info/top_level.txt
python_yuan_xuexi_shiyong_zhinan_2021_7_27_fix1-2024.3.6.0.dist-info/RECORD
